rtpplayapi/__init__.py
rtpplayapi/api.py
rtpplayapi/configuration.py
tests/__init__.py
tests/test_api.py
rtpplayapi-1.0.2.dist-info/LICENSE.md
rtpplayapi-1.0.2.dist-info/METADATA
rtpplayapi-1.0.2.dist-info/WHEEL
rtpplayapi-1.0.2.dist-info/top_level.txt
rtpplayapi-1.0.2.dist-info/RECORD
