Metadata-Version: 2.1
Name: rtpplayapi
Version: 1.0.2
Summary: An unofficial python api to fetch media from RTPPlay, based on their mobile API.
Home-page: https://github.com/guipenedo/rtp-play-api
Author: Guilherme Penedo
Author-email: nostrumg@gmail.com
License: MIT
Download-URL: https://pypi.org/project/rtpplayapi/
Keywords: rtp,rtpplay,rtp-play,api,mobile,rtp-play-api
Platform: UNKNOWN
Requires-Dist: requests
